integrated_files/Execution_unit.v
// Code your design here
module Execution_unit(
  input wire clkwire,
  input[15:0] op1, op2,
  input[7:0]  imm,
  input[3:0] instructioni, regdesti,ldsti,
  output[15:0] ALU_output,
  output[3:0] regdest, ldst, instruction,
  output wire[7:0] jump_address,
  output wire jump_selector
);
  reg [15:0] ALU_result;
  reg [3:0] npc_reg, ldsti_reg, regdesti_reg, instruction_reg;
  reg jump_selector_reg;

  assign ALU_output = ALU_result;
  assign ldst = ldsti_reg;
  assign regdest = regdesti_reg;
  assign jump_address = npc_reg;
  assign jump_selector = jump_selector_reg;
  assign instruction = instruction_reg;
  always @(posedge clkwire)
    begin
      instruction_reg = instructioni;
      jump_selector_reg = 1'b0;
      case(instructioni)
      4'b0000:
        begin
        ALU_result = op1 + op2;
          npc_reg = 0; end
      4'b0001:
        begin
        ALU_result = op1 - op2;
          npc_reg = 0;end
      4'b0010:
        begin
        ALU_result = op1*op2;
          npc_reg = 0; end
        
      4'b0011: //load word 
        begin
          npc_reg = 0; end
      
       4'b0100: //store word
        begin 
          ALU_result = op1;
          npc_reg = 0;
        end 
     
      4'b0101://beq
        begin
          ALU_result = op1 - op2;
        if(op1==op2)
          begin 
            npc_reg = imm;
            jump_selector_reg = 1'b1;
          end
          else 
            npc_reg = 0;
        end
      4'b0110:
        begin
          ALU_result = op1 - op2;
        if(op1!=op2)
          begin
            npc_reg = imm; 
            jump_selector_reg = 1'b1;
            $display(npc_reg);
          end
          else 
            npc_reg = 0;
        end
     
        default: begin 
          ALU_result = op1 + op2;
          npc_reg = 0;
        end   
      endcase
     ldsti_reg = ldsti;
     regdesti_reg = regdesti;
     
            //$display("inside exe uu: npc is:%d ",npc_reg);
    end
endmodule

integrated_files/test_bench.v
`include "Execution_unit.v"
// Code your testbench here
// or browse Examples
module test_bench;
  wire clkwire;
  reg [15:0] op1, op2;
  reg clk;
  reg [7:0] imm, npci;
  reg [3:0] ldsti, regdesti, instructioni;
  wire[15:0] ALU_output;
  wire [7:0] jump_address;
  wire jump_selector;
  wire[3:0] regdest, ldst, instruction;
  Execution_unit dut(.clkwire(clkwire), .op1(op1), .op2(op2), .imm(imm),  .regdesti(regdesti), .ldsti(ldsti), .regdest(regdest), .ldst(ldst), .instructioni(instructioni),.instruction(instruction), .jump_address(jump_address), .jump_selector(jump_selector), .ALU_output(ALU_output));
  assign clkwire = clk;
  always #2
    begin 
      //$display(clk);
      clk = ~clk;
    end
  initial
	begin
          
$dumpfile("dump.vcd");
$dumpvars;
	clk = 1'b0;
	op1 = 10; op2 = 12; imm = 15; npci = 10; regdesti = 5; ldsti= 9; instructioni = 4'b0000;
      #4  $display("operands are", op1, op2, instructioni, " (add) outputs are", instruction, ALU_output,  " ",jump_address, " ", jump_selector);

op1 = 12; op2 = 3; imm = 15; npci = 10; regdesti = 5; ldsti= 9; instructioni = 4'b0001;
      #4      $display("operands are", op1, op2, instructioni, " (sub) outputs are", instruction, ALU_output, " ",jump_address, " ", jump_selector);

op1 = 4; op2 = 7; imm = 15; npci = 10; regdesti = 5; ldsti= 9;  instructioni = 4'b0010;
      #4      $display("operands are", op1, op2, instructioni, " (mul) outputs are", instruction, ALU_output, " ",jump_address, " ", jump_selector);

op1 = 14; op2 = 14; imm = 15; npci = 10; regdesti = 5; ldsti= 9; instructioni = 4'b0101;
      #4    $display("operands are", op1, op2, instructioni, " (beq) outputs are", instruction, ALU_output, " ",jump_address, " ", jump_selector);

op1 = 18; op2 = 20; imm = 15; npci = 10;  regdesti = 5; ldsti= 9; instructioni = 4'b0110;
      #4    $display("operands are", op1, op2, instructioni, " (bnq) outputs are", instruction, ALU_output, " ",jump_address, " ", jump_selector);

op1 = 17; op2 = 18; imm = 15; npci  = 10;  regdesti = 5; ldsti= 9; instructioni = 4'b0100;
      #4    $display("operands are", op1, op2, instructioni, " (store) outputs are", instruction, ALU_output, " ",jump_address, " ", jump_selector);

op1 = 17; op2 = 18; imm = 15; npci = 10;  regdesti = 5; ldsti= 9; instructioni = 4'b0011;
      #4   $display("operands are", op1, op2, instructioni, " (load) outputs are", instruction, ALU_output, " ",jump_address, " ", jump_selector);
#2
$finish;
	end
endmodule

integrated_files/dump.vcd
$date
	Sat Oct 22 23:57:17 2022
$end
$version
	Icarus Verilog
$end
$timescale
	1s
$end
$scope module test_bench $end
$var wire 1 ! clkwire $end
$var wire 4 " regdest [3:0] $end
$var wire 4 # ldst [3:0] $end
$var wire 1 $ jump_selector $end
$var wire 8 % jump_address [7:0] $end
$var wire 4 & instruction [3:0] $end
$var wire 16 ' ALU_output [15:0] $end
$var reg 1 ( clk $end
$var reg 8 ) imm [7:0] $end
$var reg 4 * instructioni [3:0] $end
$var reg 4 + ldsti [3:0] $end
$var reg 8 , npci [7:0] $end
$var reg 16 - op1 [15:0] $end
$var reg 16 . op2 [15:0] $end
$var reg 4 / regdesti [3:0] $end
$scope module dut $end
$var wire 16 0 ALU_output [15:0] $end
$var wire 1 ! clkwire $end
$var wire 8 1 imm [7:0] $end
$var wire 4 2 instruction [3:0] $end
$var wire 4 3 instructioni [3:0] $end
$var wire 1 $ jump_selector $end
$var wire 4 4 ldst [3:0] $end
$var wire 4 5 ldsti [3:0] $end
$var wire 16 6 op1 [15:0] $end
$var wire 16 7 op2 [15:0] $end
$var wire 4 8 regdest [3:0] $end
$var wire 4 9 regdesti [3:0] $end
$var wire 8 : jump_address [7:0] $end
$var reg 16 ; ALU_result [15:0] $end
$var reg 4 < instruction_reg [3:0] $end
$var reg 1 = jump_selector_reg $end
$var reg 4 > ldsti_reg [3:0] $end
$var reg 4 ? npc_reg [3:0] $end
$var reg 4 @ regdesti_reg [3:0] $end
$upscope $end
$upscope $end
$enddefinitions $end
$comment Show the parameter values. $end
$dumpall
$end
#0
$dumpvars
bx @
bx ?
bx >
x=
bx <
bx ;
b0xxxx :
b101 9
bx 8
b1100 7
b1010 6
b1001 5
bx 4
b0 3
bx 2
b1111 1
bx 0
b101 /
b1100 .
b1010 -
b1010 ,
b1001 +
b0 *
b1111 )
0(
bx '
bx &
b0xxxx %
x$
bx #
bx "
0!
$end
#2
b101 "
b101 8
b101 @
b1001 #
b1001 4
b1001 >
b0 %
b0 :
b0 ?
b10110 '
b10110 0
b10110 ;
0$
0=
b0 &
b0 2
b0 <
1!
1(
#4
0!
0(
b1 *
b1 3
b11 .
b11 7
b1100 -
b1100 6
#6
b1001 '
b1001 0
b1001 ;
b1 &
b1 2
b1 <
1!
1(
#8
0!
0(
b10 *
b10 3
b111 .
b111 7
b100 -
b100 6
#10
b11100 '
b11100 0
b11100 ;
b10 &
b10 2
b10 <
1!
1(
#12
0!
0(
b101 *
b101 3
b1110 .
b1110 7
b1110 -
b1110 6
#14
1$
1=
b1111 %
b1111 :
b1111 ?
b0 '
b0 0
b0 ;
b101 &
b101 2
b101 <
1!
1(
#16
0!
0(
b110 *
b110 3
b10100 .
b10100 7
b10010 -
b10010 6
#18
b1111111111111110 '
b1111111111111110 0
b1111111111111110 ;
1$
1=
b110 &
b110 2
b110 <
1!
1(
#20
0!
0(
b100 *
b100 3
b10010 .
b10010 7
b10001 -
b10001 6
#22
b0 %
b0 :
b0 ?
b10001 '
b10001 0
b10001 ;
0$
0=
b100 &
b100 2
b100 <
1!
1(
#24
0!
0(
b11 *
b11 3
#26
b11 &
b11 2
b11 <
1!
1(
